LICENSE
MANIFEST.in
README.rst
setup.py
amptags/__init__.py
amptags/middleware.py
amptags/templatetags/__init__.py
amptags/templatetags/amptags.py
django_amptags.egg-info/PKG-INFO
django_amptags.egg-info/SOURCES.txt
django_amptags.egg-info/dependency_links.txt
django_amptags.egg-info/top_level.txt
tests/__init__.py
tests/test_settings.py
tests/tests.py
tests/static/tests/static_file.txt
tests/static/tests/static_file_with_escapables.txt